Metadata-Version: 1.1
Name: beginnerprofile
Version: 0.0.1
Summary: Beginner Python project
Home-page: https://https://github.com/Kerksak/beginnerprofile
Author: Kerksak Mattayangkul
Author-email: kerksak.ton@gmail.com
License: MIT
Download-URL: https://github.com/Kerksak/beginnerprofile/archive/v0.0.1.zip
Keywords: Profile,Python,Kerksak Mattayangkul
Platform: UNKNOWN
Classifier: Development Status :: 3 - Alpha
Classifier: Intended Audience :: Education
Classifier: Topic :: Utilities
Classifier: License :: OSI Approved :: MIT License
Classifier: Programming Language :: Python :: 3
Classifier: Programming Language :: Python :: 3.4
Classifier: Programming Language :: Python :: 3.5
Classifier: Programming Language :: Python :: 3.6
Classifier: Programming Language :: Python :: 3.7
Classifier: Programming Language :: Python :: 3.8
Classifier: Programming Language :: Python :: 3.9
Classifier: Programming Language :: Python :: 3.10
